LICENSE
README.md
setup.py
kratky_rg_izero/__init__.py
kratky_rg_izero/kratky_rg_izero.py
kratky_rg_izero.egg-info/PKG-INFO
kratky_rg_izero.egg-info/SOURCES.txt
kratky_rg_izero.egg-info/dependency_links.txt
kratky_rg_izero.egg-info/requires.txt
kratky_rg_izero.egg-info/top_level.txt